chameo/__init__.py
chameo/cli.py
chameo-1.0.0.dist-info/licenses/LICENSE
chameo-1.0.0.dist-info/METADATA
chameo-1.0.0.dist-info/WHEEL
chameo-1.0.0.dist-info/entry_points.txt
chameo-1.0.0.dist-info/top_level.txt
chameo-1.0.0.dist-info/RECORD
