Metadata-Version: 2.4
Name: chameo
Version: 1.0.0
Summary: CLI for Chameo template generator for Creating Reproducible Machine Learning Projects on Chameleon Cloud
Author-email: Ahmed Alghali <a7medalghali777@gmail.com>, Mohamed Saeed <mohdsaeed18x3@gmail.com>, Fraid Fund <ffund@nyu.edu>
License: MIT License
Project-URL: homepage, https://github.com/A7med7x7/Chameo
Project-URL: repository, https://github.com/A7med7x7/Chameo
Keywords: Chameleon Cloud,MLOps,MLflow,Reproducibility
Classifier: Development Status :: 5 - Production/Stable
Classifier: Environment :: GPU :: NVIDIA CUDA :: 11
Classifier: Environment :: GPU :: NVIDIA CUDA :: 12
Classifier: Environment :: OpenStack
Classifier: Framework :: Jupyter :: JupyterLab
Classifier: Intended Audience :: Science/Research
Classifier: Operating System :: MacOS
Classifier: Operating System :: Unix
Classifier: Operating System :: POSIX :: Linux
Classifier: Programming Language :: Python
Classifier: Topic :: Scientific/Engineering :: Artificial Intelligence
Requires-Python: >=3.9
License-File: LICENSE
Requires-Dist: click>=8.0
Requires-Dist: copier>=9.0
Dynamic: license-file
